ai_boutique_assit_mcp/__init__.py
ai_boutique_assit_mcp/hipstershop.proto
ai_boutique_assit_mcp/hipstershop_pb2.py
ai_boutique_assit_mcp/hipstershop_pb2_grpc.py
ai_boutique_assit_mcp/mcp_server.py
ai_boutique_assit_mcp-1.0.4.dist-info/licenses/LICENSE
ai_boutique_assit_mcp-1.0.4.dist-info/METADATA
ai_boutique_assit_mcp-1.0.4.dist-info/WHEEL
ai_boutique_assit_mcp-1.0.4.dist-info/entry_points.txt
ai_boutique_assit_mcp-1.0.4.dist-info/top_level.txt
ai_boutique_assit_mcp-1.0.4.dist-info/RECORD
