Metadata-Version: 2.4
Name: ai-boutique-assit-mcp
Version: 1.0.4
Summary: MCP Server for Online Boutique AI Assistant - exposing microservices via Model Context Protocol
Author-email: Arjun Prabhulal <code.aicloudlab@gmail.com>
License: MIT
Project-URL: Homepage, https://github.com/arjunprabhulal/ai-boutique-assit-mcp
Project-URL: Documentation, https://github.com/arjunprabhulal/ai-boutique-assit-mcp/blob/main/README.md
Project-URL: Repository, https://github.com/arjunprabhulal/ai-boutique-assit-mcp
Project-URL: Bug Reports, https://github.com/arjunprabhulal/ai-boutique-assit-mcp/issues
Keywords: mcp,model-context-protocol,microservices,grpc,kubernetes,gke,e-commerce,google-adk
Classifier: Development Status :: 5 - Production/Stable
Classifier: Intended Audience :: Developers
Classifier: License :: OSI Approved :: MIT License
Classifier: Operating System :: OS Independent
Classifier: Programming Language :: Python :: 3
Classifier: Programming Language :: Python :: 3.9
Classifier: Programming Language :: Python :: 3.10
Classifier: Programming Language :: Python :: 3.11
Classifier: Topic :: Software Development :: Libraries :: Python Modules
Classifier: Topic :: Internet :: WWW/HTTP :: HTTP Servers
Classifier: Topic :: System :: Distributed Computing
Requires-Python: >=3.9
License-File: LICENSE
Requires-Dist: uvicorn>=0.32.0
Requires-Dist: requests>=2.32.0
Requires-Dist: grpcio==1.75.0
Requires-Dist: grpcio-tools==1.75.0
Requires-Dist: protobuf<7.0.0,>=6.31.1
Requires-Dist: google-adk==1.14.1
Requires-Dist: starlette>=0.37.2
Requires-Dist: python-dotenv>=1.0.0
Requires-Dist: mcp==1.12.1
Dynamic: license-file
